memoclass/__init__.py
memoclass/memoclass.py
memoclass/memoize.py
memoclass-0.2.1.dist-info/LICENSE
memoclass-0.2.1.dist-info/METADATA
memoclass-0.2.1.dist-info/WHEEL
memoclass-0.2.1.dist-info/top_level.txt
memoclass-0.2.1.dist-info/RECORD
