Metadata-Version: 2.1
Name: memoclass
Version: 0.2.1
Summary: A utility package for memoizing functions and class methods
Home-page: https://github.com/Jon-Burr/memoclass.git
Author: Jon Burr
Author-email: jon.burr.gh@gmail.com
License: MIT
Keywords: memoize,cache
Platform: UNKNOWN
Classifier: Development Status :: 4 - Beta
Classifier: License :: OSI Approved :: MIT License
Classifier: Natural Language :: English
Classifier: Programming Language :: Python
Classifier: Programming Language :: Python :: 2.7
Classifier: Programming Language :: Python :: 3
Classifier: Programming Language :: Python :: 3.5
Classifier: Programming Language :: Python :: 3.6
Classifier: Programming Language :: Python :: 3.7
Classifier: Programming Language :: Python :: 3.8
Requires-Python: >=2.7, !=3.0.*, !=3.1.*, !=3.2.*, !=3.3.*, !=3.4.*
Requires-Dist: future
Requires-Dist: funcsigs ; python_version < "3.0"
